setup.cfg
setup.py
django_timetracker.egg-info/PKG-INFO
django_timetracker.egg-info/SOURCES.txt
django_timetracker.egg-info/dependency_links.txt
django_timetracker.egg-info/not-zip-safe
django_timetracker.egg-info/requires.txt
django_timetracker.egg-info/top_level.txt
timetracker/__init__.py
timetracker/models.py
timetracker/serializers.py
timetracker/testing_utils.py
timetracker/urls.py
timetracker/views.py
timetracker/migrations/0001_initial.py
timetracker/migrations/__init__.py
timetracker/tests/__init__.py
timetracker/tests/test_models.py
timetracker/tests/test_serializers.py
timetracker/tests/test_views.py